library/__init__.py
library/converters/__init__.py
library/converters/plink.py
library/converters/plink_bin_downloader.py
library/enums/__init__.py
library/enums/plink_filetypes.py
library/enums/plink_headers.py
library/enums/plink_keywords.py
library/tools/__init__.py
library/tools/collections.py
plynk/__init__.py
plynk/converters/__init__.py
plynk/converters/plink.py
plynk/converters/plink_bin_downloader.py
plynk/enums/__init__.py
plynk/enums/plink_filetypes.py
plynk/enums/plink_headers.py
plynk/enums/plink_keywords.py
plynk/parsers/__init__.py
plynk/parsers/plink_file_reader.py
plynk/tools/__init__.py
plynk/tools/collections.py
test/__init__.py
test/test_plink.py
test/test_plink_downloader.py
test/test_plink_file_reader.py
plynk-0.1.2.dist-info/LICENSE
plynk-0.1.2.dist-info/METADATA
plynk-0.1.2.dist-info/WHEEL
plynk-0.1.2.dist-info/top_level.txt
plynk-0.1.2.dist-info/RECORD
