Metadata-Version: 2.1
Name: plynk
Version: 0.1.2
Summary: Easy command over the PLINK software directly from Python
Home-page: https://gitlab.com/achwalt/plynk
Author: Benjamin Albrechts
Author-email: benjamin.albrechts@gmail.com
Keywords: plink genomics genetics
Classifier: License :: OSI Approved :: MIT License
Classifier: Programming Language :: Python :: 3.11
Classifier: Programming Language :: Python :: 3.12
Classifier: Programming Language :: Python :: 3.13
License-File: LICENSE
Requires-Dist: numpy ==1.26.4
Requires-Dist: pandas ==2.2.2
Requires-Dist: python-dateutil ==2.9.0.post0
Requires-Dist: pytz ==2024.1
Requires-Dist: six ==1.16.0
Requires-Dist: tzdata ==2024.1
